EasyMIDI/EasyMIDI.py
EasyMIDI/__init__.py
EasyMIDI/data/instruments.tsv
EasyMIDI/midiutil/MidiFile.py
EasyMIDI/midiutil/__init__.py
EasyMIDI-1.0.dist-info/top_level.txt
EasyMIDI-1.0.dist-info/WHEEL
EasyMIDI-1.0.dist-info/DESCRIPTION.rst
EasyMIDI-1.0.dist-info/metadata.json
EasyMIDI-1.0.dist-info/METADATA
EasyMIDI-1.0.dist-info/RECORD
