Metadata-Version: 1.1
Name: EasyMIDI
Version: 1.0
Summary: A simple, easy to use algorithmic composition MIDI creator.
Home-page: https://github.com/daviddekleer/EasyMIDI
Author: David de Kleer
Author-email: UNKNOWN
License: MIT
Download-URL: https://github.com/daviddekleer/EasyMIDI/archive/1.0.tar.gz
Keywords: Music MIDI Algorithmic Composition
Platform: Platform Independent
Classifier: Development Status :: 4 - Beta
Classifier: Intended Audience :: Developers
Classifier: Programming Language :: Python :: 3
Classifier: Programming Language :: Python :: 3.2
Classifier: Programming Language :: Python :: 3.3
Classifier: Programming Language :: Python :: 3.4
Classifier: Programming Language :: Python :: 3.5
Classifier: License :: OSI Approved :: MIT License
Classifier: Operating System :: OS Independent
Classifier: Topic :: Multimedia :: Sound/Audio :: MIDI
